zemfrog_quasar/__init__.py
zemfrog_quasar/templates/quasar/layout.html
zemfrog_quasar-1.0.2.dist-info/WHEEL
zemfrog_quasar-1.0.2.dist-info/METADATA
zemfrog_quasar-1.0.2.dist-info/RECORD
