Metadata-Version: 2.1
Name: zemfrog-quasar
Version: 1.0.2
Summary: Quasar Framework Integration
License: MIT
Keywords: zemfrog
Author: Aprila Hijriyan
Author-email: hijriyan23@gmail.com
Requires-Python: >=3.7,<4.0
Classifier: Development Status :: 4 - Beta
Classifier: Framework :: Flask
Classifier: Intended Audience :: Developers
Classifier: License :: OSI Approved :: MIT License
Classifier: Natural Language :: English
Classifier: Programming Language :: Python :: 3
Classifier: Programming Language :: Python :: 3.7
Classifier: Programming Language :: Python :: 3.8
Classifier: Programming Language :: Python :: 3.9
Requires-Dist: zemfrog-theme (>=1.0.1,<2.0.0)
Project-URL: Donation, https://www.patreon.com/aprilahijriyan
Project-URL: Github, https://github.com/zemfrog/zemfrog-quasar
Project-URL: Issue Tracker, https://github.com/zemfrog/zemfrog-quasar/issues
